cpsr/__init__.py
cpsr/cones.py
cpsr/cvxpy_interface.py
cpsr/lsqr.py
cpsr/problem.py
cpsr/refine.py
cpsr/solvers.py
cpsr/sparse_matvec.py
cpsr/utils.py
cpsr-0.0.4.dist-info/DESCRIPTION.rst
cpsr-0.0.4.dist-info/METADATA
cpsr-0.0.4.dist-info/RECORD
cpsr-0.0.4.dist-info/WHEEL
cpsr-0.0.4.dist-info/metadata.json
cpsr-0.0.4.dist-info/top_level.txt
